sklearn_surrogatesearchcv
