Metadata-Version: 2.1
Name: sklearn-surrogatesearchcv
Version: 0.1.2
Summary: Surrogate adaptive randomized search for hyper parametersin sklearn.
Home-page: https://github.com/timlyrics/sklearn_surrogatesearchcv
Author: Shaoqing Tan
Author-email: tansq7@gmail.com
License: MIT
Platform: UNKNOWN
